Workbook

Sheet Instrucciones
A1: Preguntas de evaluación del Asistente Avalanz
A3: Para qué sirve | B3: Con estas preguntas se mide qué modelo de búsqueda encuentra mejor la respuesta en los documentos reales. Son el estándar con el que se compara cada cambio del asistente.
A4: Qué llenar | B4: Solo las celdas amarillas de la hoja Preguntas (filas P01 a P25). La fila gris EJEMPLO muestra el formato y no se evalúa.
A5: Pregunta | B5: Escríbela como la haría un usuario, con sus propias palabras. No copies el título del manual: el asistente debe entender '¿cómo le doy de baja a una máquina?' aunque el manual diga 'baja de activo'.
A6: Tipo | B6: proceso (¿cómo hago...?), ubicacion (¿dónde está...?), concepto (¿qué es...?), comparacion (¿qué cambia entre...?), sin_respuesta (la respuesta no está en ningún documento).
A7: Tema y Documento | B7: Elige de las listas desplegables. Para preguntas sin respuesta usa 'ninguno' en ambos.
A8: Ubicación | B8: PDF: número de página. Word: nombre de la sección. PowerPoint: número de diapositiva. Sesión grabada: minuto aproximado (mm:ss o h:mm:ss). La hoja Documentos indica el formato de cada archivo.
A9: Respuesta esperada | B9: Uno o dos renglones con lo esencial. Sirve más adelante para medir si la respuesta del asistente es correcta.
A10: Cobertura | B10: La hoja Cobertura cuenta solas las preguntas por tema y tipo, y muestra cuántas faltan respecto a lo sugerido (25 en total, incluidas 4 sin respuesta).
A11: Importante | B11: No incluyas datos personales ni información confidencial en las preguntas: este archivo formará parte del repositorio del proyecto.

Sheet Preguntas
A1: ID | B1: Pregunta (como la haría un usuario) | C1: Tipo | D1: Tema | E1: Documento | F1: Ubicación | G1: Respuesta esperada (breve)
A2: EJEMPLO | B2: ¿Cómo le doy de baja a una máquina que ya no usamos? | C2: proceso | D2: activo-fijo | E2: manual-autocapacitacion-activo-fijo-v2.pdf | F2: 12 | G2: Se registra la baja del activo indicando motivo y fecha; el sistema calcula la depreciación pendiente.
A3: P01 | B3: ¿Cómo puedo dar de alta un activo fijjo? | C3: proceso | D3: activo-fijo | E3: manual-autocapacitacion-activo-fijo-v2.pdf | F3: 9 | G3: Un activo fijo puede generarse a partir de distintos documentos de compra. En la sesión se ingresó directamente una factura, pero el mismo dato puede jalarse desde: • Un pedido de compra. • Una orden de compra. • Una remisión (que además impacta inventarios
A4: P02 | B4: ¿Dónde puedo clasificar un activo fijo? | C4: ubicacion | D4: activo-fijo | E4: manual-autocapacitacion-activo-fijo-v2.pdf | F4: 10 | G4: Menú lateral izquierdo → Actualizaciones → Clasificación de compras. Esta pantalla muestra tanto los activos ya clasificados como los pendientes por clasificar, identificables por su fecha de adquisición
A5: P03 | B5: Estoy tratando de calcular la depreciacion mensual pero me marca un error de algo de moneda, que puede estar pasando? | C5: proceso | D5: activo-fijo | E5: manual-autocapacitacion-activo-fijo-v2.pdf | F5: 12 | G5: Los tipos de cambio de todas las monedas deben estar capturados día a día, sin huecos, desde el primer hasta el último día del periodo a calcular. El sistema no permite ejecutar el proceso si detecta días faltantes
A6: P04 | B6: Estaba tratando de calcular la depreciacion mensual y me marco un error de moneda, tu me dijiste que los tipos de cambio de todas las monedas deben de estar capturadas al dia, sin huecos, en que ruta agrego las monedas? | C6: proceso | D6: financiero | E6: manual-autocapacitacion-financiero-v2.pdf | F6: 11 | G6: El catálogo de monedas registra el tipo de cambio diario. Al iniciar sesión, el sistema solicita informar el tipo de cambio del día, normalmente a un usuario responsable de Tesorería o Contabilidad. Ya hablaste con el encargado de contabilidad para que te apoye a dar de alta la moneda?
A7: P05 | B7: Donde pudo ver los saldos bancarios ? | C7: ubicacion | D7: financiero | E7: manual-autocapacitacion-financiero-v2.pdf | F7: 20 | G7: 7.1 Saldos bancarios Financiero → Actualizaciones → Movimientos Bancarios → Saldos bancarios muestra
A8: P06 | B8: Porque no puedo anular un recibo de pago? | C8: proceso | D8: financiero | E8: manual-autocapacitacion-financiero-v2.pdf | F8: 15 | G8: En que rura estas tratando de elimnarlo ? Tu recibo esta timbrado no o ? Un recibo NO timbrado puede eliminarse directamente (Otras acciones → Borrar). Esto revierte la aplicación del cobro y regresa el saldo al título original. • Un recibo YA timbrado no puede eliminarse; debe usarse la opción Anular, que solicita el motivo de cancelación del complemento de pago ante el SAT.
A9: P07 | B9: Donde puedo revisar un proyecto? | C9: ubicacion | D9: proyectos | E9: manual-autocapacitacion-proyectos-v2.pdf | F9: 18 | G9: 1. Ve a Consultas › Consulta › Panel de proyectos. 2. Abre el Proyecto Uno (al final de la lista); es el que tiene gastos e ingresos de prueba. 3. Presiona Financiero y revisa: costo, margen, valor total y resultado. Los botones de exportar funcionan igual que en V10.
A10: P08 | B10: Oye, ya creé mi proyecto y todo, pero ahora no sé cómo asociarle los gastos. Si hago una orden de compra, ¿cómo le hago para que se vincule a ese proyecto? Antes, en la versión vieja, se hacía desde 'Vínculos', pero me dijeron que ahora hay una forma más rápida. | C10: proceso | D10: proyectos | E10: manual-autocapacitacion-proyectos-v2.pdf | F10: 12 | G10: La forma nueva (V25) es asociar desde el origen. Genera y graba el documento (ej. orden de compra), y en el listado del documento ve a Otras acciones › Asociar, elige el proyecto y la tarea. La opción antigua (desde Vínculos) sigue disponible
A11: P09 | B11: ¿Dónde puedo ver el resumen financiero completo de un proyecto, con ingresos, costos, márgenes, lo que se ha pagado y lo que se ha cobrado? | C11: ubicacion | D11: proyectos | E11: manual-autocapacitacion-proyectos-v2.pdf | F11: 18 | G11: En Consultas › Consulta › Panel de proyectos. Selecciona el proyecto y presiona el botón Financiero para ver el resumen calculado en tiempo real.
A12: P10 | B12: Oye, tengo que dar de alta a un empleado nuevo en nómina. Sé que tengo que poner su nombre y RFC, pero no sé en qué parte exactamente del sistema se hace, ni qué otros datos me pide. ¿Y cómo sé si ya se creó bien? Me dijeron que revise algo de la 'trayectoria laboral', pero no sé ni dónde está eso. | C12: proceso | D12: nomina | E12: manual-autocapacitacion-nomina-v2.pdf | F12: 21 | G12: Ve a Actualizaciones › Empleados › Empleados. Presiona Incluir y captura los datos. Al grabar, el sistema genera automáticamente un registro en 'Trayectoria laboral' y en 'Control de días derecho' (vacaciones). Verifica que estos registros se hayan creado.
A13: P11 | B13: ¿Dónde puedo ver el historial completo de un crédito Infonavit de un empleado, con todos los cambios que ha tenido (inicio, suspensión, modificación de valor)? | C13: ubicacion | D13: nomina | E13: manual-autocapacitacion-nomina-v2.pdf | F13: 19 | G13: En Actualizaciones › Empleados › Créditos Infonavit. Esta rutina nueva en V25 conserva el historial completo de movimientos del crédito, de forma independiente al maestro del empleado
A14: P12 | B14: ¿Qué es un 'mnemónico' y para qué sirve? Un compañero me dijo que son variables que se usan en las fórmulas de cálculo de nómina, pero no entiendo bien cómo funcionan ni dónde se ven. | C14: concepto | D14: nomina | E14: manual-autocapacitacion-nomina-v2.pdf | F14: 15 | G14: Los mnemónicos son variables que usa el sistema en las fórmulas de cálculo (ej. AFPPECFIN para 'Asiento Fijo Fecha Final'). Se consultan en Definición de Cálculo › Mnemónicos. No es programación, son sentencias lógicas que definen cómo se calcula cada concepto.
A15: P13 | B15: ¿Qué cambia en la forma de generar los CFDI de nómina entre la versión anterior (V10) y la nueva (V25)? Antes el PAC armaba todo el XML y el PDF, pero me dijeron que ahora es diferente. | C15: comparacion | D15: nomina | E15: manual-autocapacitacion-nomina-v2.pdf | F15: 6 | G15: En V10, el PAC armaba el XML y el PDF. En V25, el propio ERP (TOTVS) genera el XML y la representación gráfica (PDF), y el PAC solo se conserva para el timbrado final ante el SAT. Esto implica que la calidad de los datos de origen es responsabilidad directa del usuario
A16: P14 | B16: ¿Cómo puedo calcular el finiquito de un empleado que renunció y que tiene un préstamo de Fonacot activo con saldo pendiente? ¿El sistema considera automáticamente ese saldo o lo tengo que calcular yo por separado? | C16: sin_respuesta | D16: nomina | E16: manual-autocapacitacion-nomina-v2.pdf | F16: N/A | G16: No se encontró información específica en el manual sobre el tratamiento de saldos de préstamos Fonacot activos al momento de calcular un finiquito, Deseas que cree un tiquet para que un equipo funcional te contacte?
A17: P15 | B17: ¿Cómo registro un lead en Odoo y qué pasa si no tengo el RFC del cliente? Me da miedo que el sistema me bloquee o no me deje avanzar. | C17: proceso | D17: crm-odoo-dyce | E17: manual-autocapacitacion-crm-odoo-dyce-v1.docx | F17: 5.1 Concepto de contacto y lead en Odoo | G17: Ve a CRM › Leads › Nuevo. Captura nombre, venta esperada y contacto. Puedes guardar el lead sin RFC; el sistema solo te lo exigirá al convertir la oportunidad a pedido de venta.
A18: P16 | B18: Tengo una oportunidad en el CRM que ya está lista para cerrar. ¿Cómo le hago para confirmar el pedido de venta y qué documentos me va a pedir el sistema antes de dejarme? | C18: proceso | D18: crm-odoo-dyce | E18: manual-autocapacitacion-crm-odoo-dyce-v1.docx | F18: 5.7 Confirmación del pedido de venta | G18: Antes de confirmar, el sistema exige: forma de pago, política de pago, uso de CFDI, términos de pago y adjuntar evidencia de la orden de compra del cliente. También es indispensable que el cliente ya esté dado de alta en TOTVS.
A19: P17 | B19: Ya timbré una factura, pero me di cuenta de que tiene un error en el RFC del cliente. ¿Cómo la cancelo? ¿Qué pasa si ya la había contabilizado? | C19: proceso | D19: ventas-facturacion | E19: manual-autocapacitacion-ventas-facturacion-v1.docx | F19: 8.4 Cancelación de CFDI | G19: Ve a Facturación › Cancelación CFDI. Primero "Actualizar estatus" y luego elige el motivo (01, 02 o 03). Si ya estaba contabilizada, el sistema genera el asiento de reversión automáticamente.
A20: P18 | B20: ¿Dónde puedo ver un reporte de todas las ventas del mes pasado, pero que me deje filtrar por vendedor y ver el estado de entrega y de facturación al mismo tiempo? | C20: ubicacion | D20: crm-odoo-dyce | E20: manual-autocapacitacion-crm-odoo-dyce-v1.docx | F20: 5.11 Reportes y filtros | G20: Desde Ventas › Órdenes › Órdenes. Usa "Filtrar" para vendedor, rango de fechas, estado de entrega y estado de factura. Puedes agrupar por vendedor y exportar a Excel con "Acciones › Exportar".
A21: P19 | B21: Un cliente me pidió una factura pero no tengo una remisión ni un pedido de venta. ¿Puedo generar una factura manual? ¿Y cómo le hago si necesito que salga de una remisión específica? | C21: proceso | D21: ventas-facturacion | E21: manual-autocapacitacion-ventas-facturacion-v1.docx | F21: 8.1 Generación de factura | G21: Sí, se puede generar una factura manual desde Facturación › Generar notas › Factura manual. También puedes generarla desde una o varias remisiones usando el origen "Remisión" y el parámetro "Agrupa por cliente"
A22: P20 | B22: ¿Qué pasa si un técnico intenta ver los tickets de otro sistema o de otra empresa? ¿El sistema se lo permite o está restringido? | C22: concepto | D22: roles | E22: arquitectura-roles-it-service-desk.pptx | F22: 8 | G22: No se lo permite. El rol "Técnico" solo puede ver los tickets asignados a él y los que él mismo levante. No puede ver tickets de otros sistemas, personas o empresas
A23: P21 | B23: Si un empleado se va de la empresa, ¿basta con desactivar su cuenta en el sistema o hay que hacer algo más para que ya no reciba tickets ni aparezca en los buscadores? | C23: proceso | D23: roles | E23: arquitectura-roles-it-service-desk.pptx | F23: 9 | G23: No basta con desactivar. Dar de baja implica que el usuario ya no trabaja en el grupo: no aparece en los buscadores ni recibe tickets. Estar "bloqueado" es diferente; sigue siendo empleado y sigue recibiendo tickets, solo no puede entrar.
A24: P22 | B24: ¿Cómo puedo usar la IA de Claude para que me ayude a revisar qué contratos vencen en los próximos 90 días y cuáles necesitan renovación urgente? | C24: sin_respuesta | D24: ninguno | E24: ninguno | F24: N/A | G24: No se encontró información específica en los manuales de capacitación sobre el uso de Claude para consultas de vencimiento de contratos. ¿Deseas que cree un ticket para que un equipo funcional te contacte y te explique cómo aprovechar esta herramienta?
A25: P23 | B25: ¿Dónde puedo ver un dashboard que me muestre cuántos contratos se revisaron, cuántos escritos se presentaron y cuál es el cumplimiento del equipo jurídico en la semana? | C25: sin_respuesta | D25: ninguno | E25: ninguno | F25: N/A | G25: No se encontró información específica en los manuales de capacitación sobre el KPI Dashboard jurídico. ¿Deseas que cree un ticket para que un equipo funcional te contacte y te muestre cómo acceder a este reporte?
A26: P24 | B26: ¿Cómo funciona el sistema de alertas para los vencimientos de pólizas, marcas y contratos? ¿Me avisa por correo o tengo que entrar al portal a revisar? | C26: sin_respuesta | D26: ninguno | E26: ninguno | F26: N/A | G26: No se encontró información específica en los manuales de capacitación sobre el sistema de alertas de vencimientos jurídicos. ¿Deseas que cree un ticket para que un equipo funcional te contacte y te explique el funcionamiento de las alertas?
A27: P25 | B27: ¿Claude puede ayudarme a generar un contrato de NDA para una unidad de negocio específica? ¿Qué datos necesita y cómo se genera? | C27: sin_respuesta | D27: ninguno | E27: ninguno | F27: N/A | G27: No se encontró información específica en los manuales de capacitación sobre el generador de contratos con Claude. ¿Deseas que cree un ticket para que un equipo funcional te contacte y te guíe en el uso de esta herramienta?

Sheet Cobertura
A1: Cobertura de las preguntas
A3: Tema | B3: Sugeridas | C3: Escritas | D3: Faltan | F3: Nota: 'ninguno' son preguntas cuya respuesta NO está en los documentos; sirven para probar que el asistente sepa decir que no sabe.
A4: activo-fijo | B4: 3 | C4: =COUNTIF(Preguntas!$D$3:$D$27,A4) -> 3 | D4: =MAX(B4-C4,0) -> 0
A5: financiero | B5: 3 | C5: =COUNTIF(Preguntas!$D$3:$D$27,A5) -> 3 | D5: =MAX(B5-C5,0) -> 0
A6: proyectos | B6: 3 | C6: =COUNTIF(Preguntas!$D$3:$D$27,A6) -> 3 | D6: =MAX(B6-C6,0) -> 0
A7: nomina | B7: 5 | C7: =COUNTIF(Preguntas!$D$3:$D$27,A7) -> 5 | D7: =MAX(B7-C7,0) -> 0
A8: crm-odoo-dyce | B8: 2 | C8: =COUNTIF(Preguntas!$D$3:$D$27,A8) -> 3 | D8: =MAX(B8-C8,0) -> 0
A9: ventas-facturacion | B9: 3 | C9: =COUNTIF(Preguntas!$D$3:$D$27,A9) -> 2 | D9: =MAX(B9-C9,0) -> 1
A10: roles | B10: 2 | C10: =COUNTIF(Preguntas!$D$3:$D$27,A10) -> 2 | D10: =MAX(B10-C10,0) -> 0
A11: ninguno | B11: 4 | C11: =COUNTIF(Preguntas!$D$3:$D$27,A11) -> 4 | D11: =MAX(B11-C11,0) -> 0
A12: Total | B12: =SUM(B4:B11) -> 25 | C12: =SUM(C4:C11) -> 25 | D12: =SUM(D4:D11) -> 1
A14: Tipo | B14: Escritas
A15: proceso | B15: =COUNTIF(Preguntas!$C$3:$C$27,A15) -> 11
A16: ubicacion | B16: =COUNTIF(Preguntas!$C$3:$C$27,A16) -> 6
A17: concepto | B17: =COUNTIF(Preguntas!$C$3:$C$27,A17) -> 2
A18: comparacion | B18: =COUNTIF(Preguntas!$C$3:$C$27,A18) -> 1
A19: sin_respuesta | B19: =COUNTIF(Preguntas!$C$3:$C$27,A19) -> 5

Sheet Documentos
A1: Tema | B1: Archivo | C1: Formato | D1: Cómo indicar la ubicación | F1: Temas | H1: Tipos
A2: activo-fijo | B2: manual-autocapacitacion-activo-fijo-v2.pdf | C2: PDF | D2: Número de página | F2: activo-fijo | H2: proceso
A3: financiero | B3: manual-autocapacitacion-financiero-v2.pdf | C3: PDF | D3: Número de página | F3: financiero | H3: ubicacion
A4: proyectos | B4: manual-autocapacitacion-proyectos-v2.pdf | C4: PDF | D4: Número de página | F4: proyectos | H4: concepto
A5: nomina | B5: manual-autocapacitacion-nomina-v2.pdf | C5: PDF | D5: Número de página | F5: nomina | H5: comparacion
A6: nomina | B6: capacitacion-2026-09-07.transcripcion.docx | C6: Sesión grabada | D6: Minuto aproximado (mm:ss o h:mm:ss) | F6: crm-odoo-dyce | H6: sin_respuesta
A7: nomina | B7: capacitacion-2026-09-08.transcripcion.docx | C7: Sesión grabada | D7: Minuto aproximado (mm:ss o h:mm:ss) | F7: ventas-facturacion
A8: nomina | B8: prototipo-2026-09-18.transcripcion.docx | C8: Sesión grabada | D8: Minuto aproximado (mm:ss o h:mm:ss) | F8: roles
A9: nomina | B9: prototipo-2026-09-22.transcripcion.docx | C9: Sesión grabada | D9: Minuto aproximado (mm:ss o h:mm:ss) | F9: ninguno
A10: nomina | B10: prototipo-2026-09-23.transcripcion.docx | C10: Sesión grabada | D10: Minuto aproximado (mm:ss o h:mm:ss)
A11: crm-odoo-dyce | B11: manual-autocapacitacion-crm-odoo-dyce-v1.docx | C11: Word | D11: Nombre de la sección (Word no tiene páginas)
A12: ventas-facturacion | B12: manual-autocapacitacion-ventas-facturacion-v1.docx | C12: Word | D12: Nombre de la sección (Word no tiene páginas)
A13: roles | B13: arquitectura-roles-it-service-desk.pptx | C13: PowerPoint | D13: Número de diapositiva
A14: ninguno | B14: ninguno | C14: - | D14: Dejar vacío: la respuesta no está en los documentos
